oligopool/__init__.py
oligopool/acount.py
oligopool/background.py
oligopool/barcode.py
oligopool/final.py
oligopool/index.py
oligopool/lenstat.py
oligopool/merge.py
oligopool/motif.py
oligopool/pack.py
oligopool/pad.py
oligopool/primer.py
oligopool/revcomp.py
oligopool/spacer.py
oligopool/split.py
oligopool/xcount.py
oligopool/base/core_background.py
oligopool/base/core_barcode.py
oligopool/base/core_count.py
oligopool/base/core_index.py
oligopool/base/core_lenstat.py
oligopool/base/core_motif.py
oligopool/base/core_pack.py
oligopool/base/core_primer.py
oligopool/base/core_split.py
oligopool/base/phiX.py
oligopool/base/scry.py
oligopool/base/utils.py
oligopool/base/validation_parsing.py
oligopool/base/vectordb.py
oligopool-2024.12.2.dist-info/LICENSE
oligopool-2024.12.2.dist-info/METADATA
oligopool-2024.12.2.dist-info/WHEEL
oligopool-2024.12.2.dist-info/top_level.txt
oligopool-2024.12.2.dist-info/RECORD
