Metadata-Version: 2.1
Name: oligopool
Version: 2024.12.2
Summary: Oligopool Calculator - Automated design and analysis of oligopool libraries
Home-page: https://github.com/ayaanhossain/oligopool
Author: Ayaan Hossain and Howard Salis
Author-email: auh57@psu.edu, salis@psu.edu
Project-URL: Bug Reports, https://github.com/ayaanhossain/oligopool/issues
Project-URL: Source, https://github.com/ayaanhossain/oligopool/tree/master/oligopool
Keywords: synthetic computational biology nucleotide oligo pool calculator design analysis barcode primer spacer motif split pad assembly index pack scry classifier count acount xcount
Classifier: Development Status :: 4 - Beta
Classifier: Intended Audience :: Science/Research
Classifier: Topic :: Scientific/Engineering
Classifier: Topic :: Scientific/Engineering :: Bio-Informatics
Classifier: Topic :: Scientific/Engineering :: Chemistry
Classifier: License :: OSI Approved :: GNU General Public License v3 (GPLv3)
Classifier: Programming Language :: Python :: 3.10
Classifier: Programming Language :: Python :: 3.11
Classifier: Programming Language :: Python :: 3.12
Requires-Python: >=3.10, <4
License-File: LICENSE
Requires-Dist: biopython>=1.84
Requires-Dist: primer3-py>=2.0.3
Requires-Dist: msgpack>=1.1.0
Requires-Dist: pyfastx>=2.1.0
Requires-Dist: edlib>=1.3.9.post1
Requires-Dist: parasail>=1.3.4
Requires-Dist: nrpcalc>=1.7.0
Requires-Dist: sharedb>=1.1.2
Requires-Dist: numba>=0.60.0
Requires-Dist: seaborn>=0.13.2
Requires-Dist: multiprocess>=0.70.17
